<?xml version="1.0" encoding="utf-8"?>
<!--Generated by crowdin.net-->
<resources>
  <string name="app_name">システムアップデート</string>
  <string name="apply_now_button_text">すぐに更新</string>
  <string name="apply_later_button_text">後で更新</string>
  <string name="apply_update_button_text">アプリケーションの更新</string>
  <string name="apply_title_textview_text">使用準備が出来ます</string>
  <string name="apply_subtitle_textview_text">リリースノート：</string>
  <string name="apply_unable_to_reboot_toast">リカバリモードで再起動できません</string>
  <string name="apply_trying_to_get_root_access">リカバリモードで再起動するためにroot権限を取得中</string>
  <string name="available_updates_text">どのROMをダウンロードするか選択してください :</string>
  <string name="choose_available_update_text">アップグレード</string>
  <string name="no_updates_found_instructions">既に最新版でした\nクリック\'チェック中\'\更新を再確認します。</string>
  <string name="check_error_instructions">更新の確認に失敗\nクリック\'チェック中\'\更新を再確認します。</string>
  <string name="downloaded_update_found_text">SDカード中にアップデートファイルを見つけました :</string>
  <string name="checking_for_updates">アップデートを調べています</string>
  <string name="downloading_update">アップデートをダウンロードしています</string>
  <string name="sdcard_is_not_present_dialog_body">更新ファイルをダウンロードするのにSDカードが必要です</string>
  <string name="sdcard_is_not_present_dialog_title">SDカードが見つかりません</string>
  <string name="sdcard_is_not_present_dialog_ok_button">Ok</string>
  <string name="current_version_text">現在使用中のバージョン：{0}</string>
  <string name="delete_updates_text">アップデートを削除</string>
  <string name="delete_updates_success_message">このアップデートは削除されました</string>
  <string name="delete_updates_failure_message">アップデート削除エラー</string>
  <string name="delete_updates_noFolder_message">ローカルアップデートは見つかりませんでした</string>
  <string name="apply_update_dialog_title">確認してください</string>
  <string name="apply_update_dialog_text">すぐにこのファイルを使用して更新する: (0). \n"アップデート"をクリックすると、電話は自動的にリカバリーモードで再起動し更新をインストールします。</string>
  <string name="apply_update_dialog_update_button">更新</string>
  <string name="apply_update_dialog_backup_and_update_button">バックアップ＆アプリケーションの更新</string>
  <string name="apply_update_dialog_cancel_button">キャンセル</string>
  <string name="check_now">すぐに更新</string>
  <string name="menu_config">設定</string>
  <string name="menu_about">About</string>
  <string name="menu_changelog">更新履歴</string>
  <string name="cancel_download_buton_text">ダウンロードをキャンセル</string>
  <string name="confirm_download_cancelation_dialog_message">本当に現在のダウンロードをキャンセルしますか？</string>
  <string name="confirm_download_cancelation_dialog_yes">はい</string>
  <string name="confirm_download_cancelation_dialog_no">いいえ</string>
  <string name="download_canceled_toast_message">ダウンロードはキャンセルされました</string>
  <string name="verify_and_apply_dialog_title">ファイルのベリファイ中</string>
  <string name="verify_and_apply_dialog_message">MD5ファイルの検証中</string>
  <string name="apply_existing_update_md5error_message">エラー：MD5値が一致しませんでした。</string>
  <string name="file_not_found_error_message">ファイルが存在しないかアクセスできません</string>
  <string name="apply_upload_info_message">"すぐに更新"をクリックすると、更新を適用するのに電話が自動的に再起動します。バックアップジョブを使用する場合には、更新後バックアップシステムに戻ってください。</string>
  <string name="notes_about_recovery">（注意してください。将来OTA更新をサポートするためには、ROMリカバリーの互換性がなければなりません。リカバリーの互換性を確実にするために、あなたはメニュー項目の"リカバリーの再適用"で推奨リカバリーを使用することで、確実にすることができます。）</string>
  <string name="last_update_check_text">前回の更新をチェック</string>
  <string name="overwrite_update_title">更新があります</string>
  <string name="overwrite_update_summary">ROMが既に存在します。\n再ダウンロードしますか？</string>
  <string name="overwrite_update_positive">再ダウンロード</string>
  <string name="overwrite_update_negative">現在のロムを使用する</string>
  <string name="no_md5_found_summary">アップデートにMD5チェックサムがありません。\n本当にこのアップデートを検証せずに適用しますか？</string>
  <string name="no_md5_found_positive">アプリケーションの更新</string>
  <string name="no_md5_found_negative">キャンセル</string>
  <string name="notification_tickertext">アップデートをダウンロードしています</string>
  <string name="notification_finished">ダウンロード完了</string>
  <string name="stable_description">安定板</string>
  <string name="experimental_description">試験版</string>
  <string name="changelog_button_text">チェンジログ</string>
  <string name="changelog_title_rom">ROMのチェンジログ</string>
  <string name="md5_check_cancelled">MD5チェックサムのチェックは取り消されました</string>
  <string name="title_running">現在のバージョン</string>
  <string name="no_updatecheck_executed">更新のチェックは実行されていません</string>
  <string name="about_dialog_title">About</string>
  <string name="no_updates_found">更新はありません</string>
  <string name="not_new_updates_found_title">更新が見つかりました！</string>
  <string name="exception_while_downloading">ダウンロード中にエラーが出現しました</string>
  <string name="not_update_check_error_title">更新をチェックすることができません</string>
  <string name="not_update_download_error_title">更新をダウンロード中にエラーが出現しました</string>
  <string name="not_update_downloaded_title">更新のダウンロードが完了しました</string>
  <string name="not_update_downloaded_body">{0} インストールする準備ができています</string>
  <string name="download_info_filename">ファイル名：</string>
  <string name="download_info_mirror">ミラーサーバー：</string>
  <string name="download_info_downloading">ダウンロード中...</string>
  <string name="download_info_speed">ダウンロード速度：</string>
  <string name="download_info_remaining_time">残り時間：</string>
  <string name="md5_verification_failed">MD5ベリファイに失敗しました</string>
  <string name="not_new_updates_found_body">新しいバージョンが発見されました</string>
  <string name="not_network_error">ネットワークエラー、インターネット接続を確認してください</string>
  <string name="version_description">バージョンの説明</string>
  <string name="acknowledge">謝意</string>
  <string name="pleasea_check_update">更新をチェックしてください</string>
  <string name="already_applied">適用済み</string>
  <string name="stable_version">安定版</string>
  <string name="test_version">ベータ版</string>
  <string name="wifi_not_available_title">WIFI未接続</string>
  <string name="wifi_not_available_body">ROMのファイルサイズは大きいので、ダウンロードにはWi-Fi接続を推奨します。Wi-Fi接続が無効化されているか接続されていなくても、続行しますか？</string>
  <string name="widget_title">My MIUI</string>
  <string name="widget_feedback">何かフィードバックがありますか？</string>
  <string name="unable_to_flash_recovery">リカバリーの適用に失敗しました</string>
  <string name="flash_recovery_successfully">リカバリーの適用に成功しました</string>
  <string name="reflash_recovery">リカバリーの再適用</string>
  <string name="boot_recovery">リカバリーに再起動します</string>
  <string name="flash_recovery_dialog_message">リカバリーの更新中</string>
  <string name="applying_rom_message">新しいROMの適用中</string>
  <string name="loading">MIUIに接続しています</string>
  <string name="page_error_title">アクセスできません</string>
  <string name="page_error">MIUIにアクセスできません。インターネット接続かサーバ側に問題があります。</string>
  <string name="page_reload">また試してください</string>
  <string name="install_rom_from_sd">SDカードからのROMのインストール</string>
</resources>
